bitcointrade/__init__.py
bitcointrade/api.py
bitcointrade/errors.py
bitcointrade/private_api.py
bitcointrade/utils.py
bitcointrade-0.7.0.dist-info/METADATA
bitcointrade-0.7.0.dist-info/RECORD
bitcointrade-0.7.0.dist-info/WHEEL
bitcointrade-0.7.0.dist-info/top_level.txt
